nymph/__init__.py
nymph/core/__init__.py
nymph/core/base.py
nymph/core/config.py
nymph/data/__init__.py
nymph/data/dataset.py
nymph/data/field.py
nymph/data/processor.py
nymph/data/scale.py
nymph/data/tokenize.py
nymph/data/tool.py
nymph/data/vocab.py
nymph/models/__init__.py
nymph/models/bi_lstm_crf.py
nymph/models/linear.py
nymph/models/tool.py
nymph/modules/__init__.py
nymph/modules/norm_classifier.py
nymph/modules/seq_classifier.py
nymph/modules/tool.py
nymph/process/__init__.py
nymph/process/metric.py
nymph/process/train.py
nymph/utils/__init__.py
nymph/utils/seed.py
nymph/utils/third/__init__.py
nymph/utils/third/doc_parse.py
nymph/utils/third/pdf_parse.py
nymph-0.2.4.dist-info/LICENSE
nymph-0.2.4.dist-info/METADATA
nymph-0.2.4.dist-info/WHEEL
nymph-0.2.4.dist-info/top_level.txt
nymph-0.2.4.dist-info/RECORD
