Metadata-Version: 2.1
Name: nymph
Version: 0.2.4
Summary: General multi-feature classification library based on pytorch
Home-page: https://github.com/smilelight/nymph
Author: lightsmile
Author-email: iamlightsmile@gmail.com
License: Apache-2.0
Platform: UNKNOWN
Classifier: Development Status :: 4 - Beta
Classifier: Operating System :: OS Independent
Classifier: Intended Audience :: Developers
Classifier: Programming Language :: Python :: 3.6
Classifier: Programming Language :: Python :: 3.7
Classifier: Topic :: Software Development :: Libraries
Requires-Dist: tqdm (>=4.47.0)
Requires-Dist: lightUtils (>=0.1.13.1)
Requires-Dist: scikit-learn (>=0.23.1)
Requires-Dist: pandas (>=1.0.5)
Requires-Dist: numpy (>=1.19.0)
Requires-Dist: torch (>=1.4.0)
Requires-Dist: pytorch-crf (>=0.7.2)
